jupyterlab_materialdarker_theme/__init__.py
jupyterlab_materialdarker_theme/_version.py
jupyterlab_materialdarker_theme-0.1.5.data/data/share/jupyter/labextensions/jupyterlab_materialdarker_theme/build_log.json
jupyterlab_materialdarker_theme-0.1.5.data/data/share/jupyter/labextensions/jupyterlab_materialdarker_theme/package.json
jupyterlab_materialdarker_theme-0.1.5.data/data/share/jupyter/labextensions/jupyterlab_materialdarker_theme/static/lib_index_js.5b286dbd43364f919151.js
jupyterlab_materialdarker_theme-0.1.5.data/data/share/jupyter/labextensions/jupyterlab_materialdarker_theme/static/lib_index_js.5b286dbd43364f919151.js.map
jupyterlab_materialdarker_theme-0.1.5.data/data/share/jupyter/labextensions/jupyterlab_materialdarker_theme/static/remoteEntry.6384b1a978b9d9f3c26b.js
jupyterlab_materialdarker_theme-0.1.5.data/data/share/jupyter/labextensions/jupyterlab_materialdarker_theme/static/remoteEntry.6384b1a978b9d9f3c26b.js.map
jupyterlab_materialdarker_theme-0.1.5.data/data/share/jupyter/labextensions/jupyterlab_materialdarker_theme/static/style.js
jupyterlab_materialdarker_theme-0.1.5.data/data/share/jupyter/labextensions/jupyterlab_materialdarker_theme/themes/jupyterlab_materialdarker_theme/index.css
jupyterlab_materialdarker_theme-0.1.5.data/data/share/jupyter/labextensions/jupyterlab_materialdarker_theme/themes/jupyterlab_materialdarker_theme/index.js
jupyterlab_materialdarker_theme-0.1.5.data/data/share/jupyter/labextensions/jupyterlab_materialdarker_theme/install.json
jupyterlab_materialdarker_theme-0.1.5.dist-info/METADATA
jupyterlab_materialdarker_theme-0.1.5.dist-info/WHEEL
jupyterlab_materialdarker_theme-0.1.5.dist-info/licenses/LICENSE
jupyterlab_materialdarker_theme-0.1.5.dist-info/RECORD
